task_track/track.py
task_track-0.0.11.dist-info/METADATA
task_track-0.0.11.dist-info/WHEEL
task_track-0.0.11.dist-info/entry_points.txt
task_track-0.0.11.dist-info/licenses/LICENSE
task_track-0.0.11.dist-info/RECORD
