Metadata-Version: 2.3
Name: task-track
Version: 0.0.11
Summary: A dead simple cli time tracker
Project-URL: Homepage, https://github.com/ostin-r/task-track
Author-email: Austin Richards <austinjrichards@outlook.com>
License-File: LICENSE
Classifier: License :: OSI Approved :: MIT License
Classifier: Operating System :: OS Independent
Classifier: Programming Language :: Python :: 3
Requires-Python: >=3.8
Requires-Dist: tabulate
